frida_mcp/cli.py
iflow_mcp_dnakov_frida_mcp-0.1.1.dist-info/METADATA
iflow_mcp_dnakov_frida_mcp-0.1.1.dist-info/WHEEL
iflow_mcp_dnakov_frida_mcp-0.1.1.dist-info/entry_points.txt
iflow_mcp_dnakov_frida_mcp-0.1.1.dist-info/licenses/LICENSE
iflow_mcp_dnakov_frida_mcp-0.1.1.dist-info/RECORD
